CHANGES.txt
LICENSE.txt
MANIFEST.in
README.txt
setup.py
js/__init__.py
js.classy.egg-info/PKG-INFO
js.classy.egg-info/SOURCES.txt
js.classy.egg-info/dependency_links.txt
js.classy.egg-info/entry_points.txt
js.classy.egg-info/namespace_packages.txt
js.classy.egg-info/not-zip-safe
js.classy.egg-info/requires.txt
js.classy.egg-info/top_level.txt
js/classy/__init__.py
js/classy/test_classy.txt
js/classy/resources/README.txt
js/classy/resources/classy.js