Metadata-Version: 1.0
Name: js.classy
Version: 1.4
Summary: Fanstatic packaging of Classy
Home-page: UNKNOWN
Author: Stephane Klein
Author-email: stephane@harobed.org
License: BSD
Platform: UNKNOWN
